{
  "type": "accessories",
  "title": "Diving Gear",
  "summaries": [
    "The <b>Diving Gear</b> is an <linked>accessory</linked> which allows the user to swim and breathe underwater for an extended amount of time. It combines the functionality of the <linked>Flipper</linked> and <linked>Diving Helmet</linked>. Apart from combining the two effects into a single accessory, it does not have other unique properties."
  ],
  "statistics": {
    "Tooltip": "<i><span class=\"gameText\">Grants the ability to swim<br>Greatly extends underwater breathing</span></i>",
    "Rarity": "<span class=\"rarity\"><linked>[img:Rarity level: 4]</linked></span>",
    "Sell": "<span class=\"coin\" title=\"2 Gold Coins\" data-sort-value=\"20000\"><span class=\"gc\">2<i> GC</i></span></span>",
    "Research": "<abbr class=\"mode-exclusive journey\" title=\"Journey Mode\">1 required</abbr>"
  },
  "crafts": {
    "<span class=\"mw-headline\" id=\"Recipes\">Recipes</span>": [
      {
        "result": {
          "rowspan": 1,
          "value": "<span class=\"i multi-line\"><linked>[img:Diving Gear]</linked><span><span><linked>Diving Gear</linked></span></span></span>"
        },
        "ingredients": {
          "value": "<ul><li><span class=\"i\"><linked>[img:Flipper]</linked><span><span><linked>Flipper</linked></span></span></span></li><li><span class=\"i\"><linked>[img:Diving Helmet]</linked><span><span><linked>Diving Helmet</linked></span></span></span></li></ul>"
        },
        "station": {
          "rowspan": 1,
          "value": "<span class=\"i\"><linked>[img:Tinkerer's Workshop]</linked><span><span><linked>Tinkerer's Workshop</linked></span></span></span>"
        }
      }
    ],
    "<span class=\"mw-headline\" id=\"Used_in\">Used in</span>": [
      {
        "result": {
          "rowspan": 1,
          "value": "<span class=\"i multi-line\"><linked>[img:Jellyfish Diving Gear]</linked><span><span><linked>Jellyfish Diving Gear</linked></span></span></span>"
        },
        "ingredients": {
          "value": "<ul><li><span class=\"i\"><linked>[img:Diving Gear]</linked><span><span><linked>Diving Gear</linked></span></span></span></li><li><span class=\"i\"><linked>[img:Jellyfish Necklace]</linked><span><span><linked>Jellyfish Necklace</linked></span></span></span></li></ul>"
        },
        "station": {
          "rowspan": 1,
          "value": "<span class=\"i\"><linked>[img:Tinkerer's Workshop]</linked><span><span><linked>Tinkerer's Workshop</linked></span></span></span>"
        }
      }
    ]
  }
}