{
  "type": "wings",
  "title": "Fin Wings",
  "summaries": [
    "1/70 chance for every <linked>quest</linked> after 10th quest in <linked>Hardmode</linked> only.",
    "<span class=\"eico s i3 i5\" title=\"Old-gen console and 3DS versions\"><b></b><i></i></span> Does not offer any horizontal flight speed bonus."
  ],
  "statistics": {
    "Time": "2.17  1.67",
    "Height": "67  53",
    "Horizontal": "34  15",
    "Vertical": "150%",
    "Rarity": "[img:Rarity level: 4]"
  },
  "source": "Quest reward from <linked>Angler</linked>"
}