{
  "type": "wings",
  "title": "Flame Wings",
  "summaries": [
    "Particle effect emits orange light, glows in the dark and appears translucent."
  ],
  "statistics": {
    "Time": "2.67",
    "Height": "81",
    "Horizontal": "38",
    "Vertical": "150%",
    "Rarity": "[img:Rarity level: 5]"
  },
  "source": "<div class=\"crafting-ingredients\"><div class=\"recipe ingredients\"><ul><li><span class=\"i\">[img:Soul of Flight]<span><span>Soul of Flight</span></span></span> <span class=\"note-text\">(20)</span></li><li><span class=\"i\">[img:Fire Feather]<span><span>Fire Feather</span></span></span></li></ul></div></div>"
}