{
  "type": "dyes",
  "title": "Flame Dye",
  "summaries": [],
  "statistics": {
    "Ingredients": "[img:Red Dye]Red Dye + [img:Orange Dye]Orange Dye + [img:Yellow Dye]Yellow Dye",
    "Crafts": "[img:Flame and Black Dye]Flame and Black Dye [img:Flame and Silver Dye]Flame and Silver Dye [img:Intense Flame Dye]Intense Flame Dye"
  },
  "source": "<linked>[img:Flame and Black Dye]</linked><br><linked>Flame and Black Dye</linked> <linked>[img:Flame and Silver Dye]</linked><br><linked>Flame and Silver Dye</linked> <linked>[img:Intense Flame Dye]</linked><br><linked>Intense Flame Dye</linked>"
}