{
  "type": "weapons",
  "title": "Mace",
  "summaries": [
    "The <b>Mace</b> is a <linked>flail</linked> found in <linked>Gold Chests</linked> located in the <linked>Underground</linked>. It can be crafted into the <linked>Flaming Mace</linked>, which inflicts the <linked>On Fire!</linked> <linked>debuff</linked>.",
    "Its best <linked>modifier</linked> is <b>Godly</b> or <b>Demonic</b>. Both modifiers increase the average damage output by the same amount."
  ],
  "statistics": {
    "Damage": "18 <span class=\"small-bold\">(Melee)</span>",
    "Knockback": "4.6 <span class=\"knockback\">(Average)</span>",
    "Critical chance": "4%",
    "Use time": "45 <span class=\"usetime\">(Very slow)</span>",
    "Velocity": "11",
    "Tooltip": "<i><span class=\"gameText\">Can be upgraded with torches</span></i>",
    "Rarity": "<span class=\"rarity\"><linked>[img:Rarity level: 1]</linked></span>",
    "Sell": "<span class=\"coin\" title=\"2 Gold Coins\" data-sort-value=\"20000\"><span class=\"gc\">2<i> GC</i></span></span>",
    "Research": "<abbr class=\"mode-exclusive journey\" title=\"Journey Mode\">1 required</abbr>"
  },
  "crafts": {
    "<span class=\"mw-headline\" id=\"Used_in\">Used in</span>": [
      {
        "result": {
          "rowspan": 1,
          "value": "<span class=\"i multi-line\"><linked>[img:Flaming Mace]</linked><span><span><linked>Flaming Mace</linked></span><span class=\"eico s i1 i2 i4\" title=\"Desktop, Console and Mobile versions\"><b></b><i></i><span>(Desktop, Console and Mobile versions)</span></span></span></span>"
        },
        "ingredients": {
          "value": "<ul><li><span class=\"i\"><linked>[img:Mace]</linked><span><span><linked>Mace</linked></span><span class=\"eico s i1 i2 i4\" title=\"Desktop, Console and Mobile versions\"><b></b><i></i><span>(Desktop, Console and Mobile versions)</span></span></span></span></li><li><span class=\"i\"><linked>[img:Torch]</linked><span><span><linked>Torch</linked></span></span></span><span class=\"am\">99</span></li></ul>"
        },
        "station": {
          "rowspan": 1,
          "value": "<linked>By Hand</linked>"
        }
      }
    ]
  }
}