{"type":"weapons","title":"Tactical Shotgun","summaries":["The <b>Tactical Shotgun</b> is a Hardmode, post-Plantera ranged weapon. It is an upgraded version of the Shotgun, auto-firing six spread shots per bullet consumed (against the Shotgun's average of four), for a possible combined base damage of 174 per bullet spent (not including bullet damage stats which are then added). It has a 8.33% / <abbr class=\"expert\" title=\"Expert Mode\">15.97%</abbr> (1/12 / <abbr class=\"expert\" title=\"Expert Mode\">23/144</abbr>) chance to drop from Tactical Skeletons in the post-Plantera Dungeon.","Its best modifier is <b>Unreal</b>."],"statistics":{"Uses ammo":"Bullets","Damage":"29 <span class=\"small-bold\">(Ranged)</span>","Knockback":"7 <span class=\"knockback\">(Strong)</span>","Critical chance":"4%","Use time":"34 <span class=\"usetime\">(Slow)</span>","Velocity":"6","Rarity":"<span class=\"rarity\">[img:Rarity level: 8]</span>","Sell":"<span class=\"coin\" title=\"8 Gold Coins\" data-sort-value=\"80000\"><span class=\"gc\">8</span></span>","Research":"<abbr class=\"journey\" title=\"Journey Mode\">1 required</abbr>"},"crafts":{}}