{
  "type": "tools",
  "title": "Terra Blade",
  "toolpower": [],
  "summaries": [
    "The <b>Terra Blade</b> is a Hardmode projectile sword. When used, it fires a green sword-shaped projectile which costs neither mana nor ammunition, deals <span class=\"eico i1 i2 i4\" title=\"Desktop, Console and Mobile versions\"><b></b><i></i></span> 50% / <span class=\"eico i6\" title=\"Legacy tModLoader version\"><b></b><i></i></span> 25% more damage than the sword, and can pierce through two enemies, dissipating after hitting a third enemy or a wall. The projectile can travel up to 5000 feet (2500 blocks) at a speed of <abbr title=\"61 miles per hour (as measured by the Stopwatch item) or 45 tiles per second\" class=\"nowrap\"><span class=\"gameText\">61 mph</span></abbr>.",
    "<ul><li>On the [img:Desktop version] Desktop version, [img:Console version] Console version, and [img:Mobile version] Mobile version, the Terra Blade becomes available after defeating Plantera.</li><li>On other versions, obtaining it requires defeating <span class=\"eico i3 i5\" title=\"Old-gen console and 3DS versions\"><b></b><i></i></span> one / <span class=\"eico i6\" title=\"Legacy tModLoader version\"><b></b><i></i></span> all mechanical bosses.</li></ul>",
    "Its best modifier is <b>Legendary</b>."
  ],
  "statistics": {
    "Damage": "85 <span class=\"eico s i1 i2 i4\" title=\"Desktop, Console and Mobile versions\"><b></b><i></i></span> / 95 <span class=\"eico s i6\" title=\"Legacy tModLoader version\"><b></b><i></i></span> / 88 <span class=\"eico s i3 i5\" title=\"Old-gen console and 3DS versions\"><b></b><i></i></span> <span class=\"small-bold\">(Melee)</span>",
    "Knockback": "6.5 <span class=\"knockback\">(Strong)</span>",
    "Critical chance": "4%",
    "Use time": "18 <span class=\"usetime\">(Very fast)</span> <span class=\"eico s i1 i2 i4\" title=\"Desktop, Console and Mobile versions\"><b></b><i></i></span> /<br> 16 <span class=\"usetime\">(Very fast)</span> <span class=\"eico s i3 i5 i6\" title=\"Old-gen console, 3DS and Legacy tModLoader versions\"><b></b><i></i></span>",
    "Velocity": "12",
    "Rarity": "<span class=\"rarity\">[img:Rarity level: 8]</span>",
    "Sell": "<span class=\"coin\" title=\"20 Gold Coins\" data-sort-value=\"200000\"><span class=\"gc\">20</span></span>",
    "Research": "<abbr class=\"journey\" title=\"Journey Mode\">1 required</abbr>"
  },
  "crafts": {
    "Recipes": [
      {
        "result": {
          "rowspan": 1,
          "value": "<span class=\"i multi-line\">[img:Terra Blade]<span><span>Terra Blade</span></span></span> ([img:Desktop version] [img:Console version] [img:Old-gen console version] [img:Mobile version] [img:Nintendo 3DS version])"
        },
        "ingredients": {
          "value": "<ul><li><span class=\"i\">[img:True Night's Edge]<span><span>True Night's Edge</span></span></span></li><li><span class=\"i\">[img:True Excalibur]<span><span>True Excalibur</span></span></span></li><li><span class=\"i\">[img:Broken Hero Sword]<span><span>Broken Hero Sword</span></span></span></li></ul>"
        },
        "station": {
          "rowspan": 2,
          "value": "<span class=\"i\">[img:Mythril Anvil]<span><span>Mythril Anvil</span></span></span><br><i><b>or</b></i><br><span class=\"i\">[img:Orichalcum Anvil]<span><span>Orichalcum Anvil</span></span></span>"
        }
      },
      {
        "result": {
          "rowspan": 1,
          "value": "<span class=\"i multi-line\">[img:Terra Blade]<span><span>Terra Blade</span></span></span> ([img:Legacy tModLoader version])"
        },
        "ingredients": {
          "value": "<ul><li><span class=\"i\">[img:True Night's Edge]<span><span>True Night's Edge</span></span></span></li><li><span class=\"i\">[img:True Excalibur]<span><span>True Excalibur</span></span></span></li></ul>"
        }
      }
    ],
    "Used in": [
      {
        "result": {
          "rowspan": 1,
          "value": "<span class=\"i multi-line\">[img:Zenith]<span><span>Zenith</span><span class=\"eico s i1 i2 i4\" title=\"Desktop, Console and Mobile versions\"><b></b><i></i></span></span></span>"
        },
        "ingredients": {
          "value": "<ul><li><span class=\"i\">[img:Terra Blade]<span><span>Terra Blade</span></span></span></li><li><span class=\"i\">[img:Meowmere]<span><span>Meowmere</span><span class=\"eico s i1 i2 i4 i6\" title=\"Desktop, Console, Mobile and Legacy tModLoader versions\"><b></b><i></i></span></span></span></li><li><span class=\"i\">[img:Star Wrath]<span><span>Star Wrath</span><span class=\"eico s i1 i2 i4 i6\" title=\"Desktop, Console, Mobile and Legacy tModLoader versions\"><b></b><i></i></span></span></span></li><li><span class=\"i\">[img:Influx Waver]<span><span>Influx Waver</span><span class=\"eico s i1 i2 i4 i6\" title=\"Desktop, Console, Mobile and Legacy tModLoader versions\"><b></b><i></i></span></span></span></li><li><span class=\"i\">[img:The Horseman's Blade]<span><span>The Horseman's Blade</span></span></span></li><li><span class=\"i\">[img:Seedler]<span><span>Seedler</span><span class=\"eico s i1 i2 i4 i6\" title=\"Desktop, Console, Mobile and Legacy tModLoader versions\"><b></b><i></i></span></span></span></li><li><span class=\"i\">[img:Starfury]<span><span>Starfury</span></span></span></li><li><span class=\"i\">[img:Bee Keeper]<span><span>Bee Keeper</span></span></span></li><li><span class=\"i\">[img:Enchanted Sword]<span><span>Enchanted Sword</span></span></span></li><li><span class=\"i\">[img:Copper Shortsword]<span><span>Copper Shortsword</span></span></span></li></ul>"
        },
        "station": {
          "rowspan": 1,
          "value": "<span class=\"i\">[img:Mythril Anvil]<span><span>Mythril Anvil</span></span></span><br><i><b>or</b></i><br><span class=\"i\">[img:Orichalcum Anvil]<span><span>Orichalcum Anvil</span></span></span>"
        }
      }
    ]
  }
}